typed_uuid/__init__.py
typed_uuid/core.py
typed_uuid/exceptions.py
typed_uuid/utils.py
typed_uuid/adapters/__init__.py
typed_uuid/adapters/fastapi.py
typed_uuid/adapters/pydantic.py
typed_uuid/adapters/sqlalchemy.py
typed_uuid-1.1.0.dist-info/METADATA
typed_uuid-1.1.0.dist-info/WHEEL
typed_uuid-1.1.0.dist-info/licenses/LICENSE
typed_uuid-1.1.0.dist-info/RECORD
