Metadata-Version: 2.4
Name: typed-uuid
Version: 1.1.0
Summary: Type-safe UUID management with prefix identification for Python
Project-URL: Homepage, https://github.com/boxcake/TypedUUID
Project-URL: Documentation, https://github.com/boxcake/TypedUUID#readme
Project-URL: Repository, https://github.com/boxcake/TypedUUID
Project-URL: Issues, https://github.com/boxcake/TypedUUID/issues
Author: TypedUUID Contributors
License-Expression: MIT
License-File: LICENSE
Keywords: fastapi,identifier,pydantic,sqlalchemy,type-safe,typed,uuid
Classifier: Development Status :: 5 - Production/Stable
Classifier: Intended Audience :: Developers
Classifier: License :: OSI Approved :: MIT License
Classifier: Operating System :: OS Independent
Classifier: Programming Language :: Python :: 3
Classifier: Programming Language :: Python :: 3.10
Classifier: Programming Language :: Python :: 3.11
Classifier: Programming Language :: Python :: 3.12
Classifier: Programming Language :: Python :: 3.13
Classifier: Topic :: Software Development :: Libraries :: Python Modules
Classifier: Typing :: Typed
Requires-Python: >=3.10
Provides-Extra: all
Requires-Dist: fastapi>=0.100.0; extra == 'all'
Requires-Dist: pydantic-core>=2.0; extra == 'all'
Requires-Dist: pydantic>=2.0; extra == 'all'
Requires-Dist: sqlalchemy>=1.4; extra == 'all'
Provides-Extra: dev
Requires-Dist: fastapi>=0.100.0; extra == 'dev'
Requires-Dist: pydantic-core>=2.0; extra == 'dev'
Requires-Dist: pydantic>=2.0; extra == 'dev'
Requires-Dist: pytest-cov>=4.0; extra == 'dev'
Requires-Dist: pytest>=7.0; extra == 'dev'
Requires-Dist: sqlalchemy>=1.4; extra == 'dev'
Provides-Extra: fastapi
Requires-Dist: fastapi>=0.100.0; extra == 'fastapi'
Requires-Dist: pydantic-core>=2.0; extra == 'fastapi'
Requires-Dist: pydantic>=2.0; extra == 'fastapi'
Provides-Extra: pydantic
Requires-Dist: pydantic-core>=2.0; extra == 'pydantic'
Requires-Dist: pydantic>=2.0; extra == 'pydantic'
Provides-Extra: sqlalchemy
Requires-Dist: sqlalchemy>=1.4; extra == 'sqlalchemy'
